{
  "botMeta": {
    "botName": "WIF",
    "asset": "WIF"
  },
  "signalBotSourceMeta": {
    "optimizedPeriod": "90 Days",
    "exchange": "Bitget",
    "timeframe": "150m",
    "signalSetting": 5,
    "baseline": "SMA",
    "baselineValue": 30,
    "slType": "ATR",
    "slValue": 3.2
  },
  "sourcePerformanceMeta": {
    "performance30d": 46.44,
    "performance90d": 281.87,
    "performance180d": null,
    "performance360d": null,
    "winrate": 55.56,
    "profitFactor": 2.848
  },
  "defaultProfile": "balanced",
  "profiles": {
    "safe": {
      "strategy": {
        "tpTargetsPercent": [1.31, 3.51, 7.48, 11.15, 15.08, 22.75],
        "tpAllocationsPercent": [26, 25, 15, 14, 11, 9],
        "stopLossPercent": 3,
        "slToBeTrigger": "TP3",
        "leverage": 3
      },
      "performanceMeta": {
        "tradeCount": 27,
        "winrate": 55.56,
        "netProfit": 281.87,
        "maxDrawdown": -17.19,
        "avgTradeProfit": 10.44
      }
    },
    "balanced": {
      "strategy": {
        "tpTargetsPercent": [1.97, 5.67, 9.26, 12.32, 16.91, 26.92],
        "tpAllocationsPercent": [8, 27, 25, 24, 8, 8],
        "stopLossPercent": 3,
        "slToBeTrigger": "TP3",
        "leverage": 7
      },
      "performanceMeta": {
        "tradeCount": 27,
        "winrate": 51.85,
        "netProfit": 2658.67,
        "maxDrawdown": -37.59,
        "avgTradeProfit": 98.47
      }
    },
    "aggressive": {
      "strategy": {
        "tpTargetsPercent": [2.67, 6.29, 9.65, 12.61, 17.03, 29.1],
        "tpAllocationsPercent": [8, 11, 27, 24, 22, 8],
        "stopLossPercent": 2,
        "slToBeTrigger": "TP3",
        "leverage": 7
      },
      "performanceMeta": {
        "tradeCount": 27,
        "winrate": 40.74,
        "netProfit": 1997.98,
        "maxDrawdown": -44.13,
        "avgTradeProfit": 74
      }
    }
  }
}
