{
  "botMeta": {
    "botName": "BERA",
    "asset": "BERA"
  },
  "signalBotSourceMeta": {
    "optimizedPeriod": "2026-05-08 activation",
    "exchange": "Bybit",
    "timeframe": "168m",
    "signalSetting": 5,
    "baseline": "TMA",
    "baselineValue": 25,
    "slType": "ATR",
    "slValue": 2
  },
  "sourcePerformanceMeta": {
    "performance30d": 9.08,
    "performance90d": 11.1,
    "performance180d": 18.49,
    "performance360d": null,
    "winrate": 77.78,
    "profitFactor": 1.467
  },
  "defaultProfile": "balanced",
  "profiles": {
    "safe": {
      "strategy": {
        "tpTargetsPercent": [
          1.39,
          2.04,
          3.52,
          4.86,
          11.48,
          18.07
        ],
        "tpAllocationsPercent": [
          27,
          23,
          18,
          15,
          10,
          7
        ],
        "stopLossPercent": 4,
        "slToBeTrigger": "TP1",
        "leverage": 1
      },
      "performanceMeta": {
        "tradeCount": 45,
        "winrate": 77.78,
        "netProfit": 18.49,
        "maxDrawdown": -11.47,
        "avgTradeProfit": 0.41
      }
    },
    "balanced": {
      "strategy": {
        "tpTargetsPercent": [
          1.93,
          2.44,
          4.37,
          8.61,
          14.73,
          19.63
        ],
        "tpAllocationsPercent": [
          13,
          18,
          22,
          22,
          17,
          8
        ],
        "stopLossPercent": 4,
        "slToBeTrigger": "TP1",
        "leverage": 3
      },
      "performanceMeta": {
        "tradeCount": 45,
        "winrate": 71.11,
        "netProfit": 117.7,
        "maxDrawdown": -28.35,
        "avgTradeProfit": 2.62
      }
    },
    "aggressive": {
      "strategy": {
        "tpTargetsPercent": [
          2.22,
          4.18,
          6.41,
          11.48,
          15.94,
          22.88
        ],
        "tpAllocationsPercent": [
          8,
          10,
          21,
          26,
          25,
          10
        ],
        "stopLossPercent": 4,
        "slToBeTrigger": "TP1",
        "leverage": 5
      },
      "performanceMeta": {
        "tradeCount": 45,
        "winrate": 66.67,
        "netProfit": 476.54,
        "maxDrawdown": -47.35,
        "avgTradeProfit": 10.59
      }
    }
  },
  "quality": {
    "metric": "composite",
    "threshold": 60,
    "candleInterval": 60,
    "notionalMultiplier": 2.0
  }
}